ujson_delta/__init__.py
ujson_delta/_diff.py
ujson_delta/_patch.py
ujson_delta/_udiff.py
ujson_delta/_upatch.py
ujson_delta/_util.py
ujson_delta-1.1.3.data/scripts/json_cat
ujson_delta-1.1.3.data/scripts/json_diff
ujson_delta-1.1.3.data/scripts/json_patch
ujson_delta-1.1.3.dist-info/DESCRIPTION.rst
ujson_delta-1.1.3.dist-info/METADATA
ujson_delta-1.1.3.dist-info/RECORD
ujson_delta-1.1.3.dist-info/WHEEL
ujson_delta-1.1.3.dist-info/metadata.json
ujson_delta-1.1.3.dist-info/top_level.txt
ujson_delta-1.1.3.dist-info/zip-safe
